odoo/addons/stock_location_package_restriction/README.rst
odoo/addons/stock_location_package_restriction/__init__.py
odoo/addons/stock_location_package_restriction/__manifest__.py
odoo/addons/stock_location_package_restriction/i18n/stock_location_package_restriction.pot
odoo/addons/stock_location_package_restriction/migrations/14.0.1.1.0/pre-migrate.py
odoo/addons/stock_location_package_restriction/models/__init__.py
odoo/addons/stock_location_package_restriction/models/stock_location.py
odoo/addons/stock_location_package_restriction/models/stock_move.py
odoo/addons/stock_location_package_restriction/readme/CONTRIBUTORS.rst
odoo/addons/stock_location_package_restriction/readme/DESCRIPTION.rst
odoo/addons/stock_location_package_restriction/readme/USAGE.rst
odoo/addons/stock_location_package_restriction/static/description/icon.png
odoo/addons/stock_location_package_restriction/static/description/index.html
odoo/addons/stock_location_package_restriction/tests/__init__.py
odoo/addons/stock_location_package_restriction/tests/test_stock_move.py
odoo/addons/stock_location_package_restriction/views/stock_location.xml
odoo14_addon_stock_location_package_restriction-14.0.1.2.1.dist-info/METADATA
odoo14_addon_stock_location_package_restriction-14.0.1.2.1.dist-info/WHEEL
odoo14_addon_stock_location_package_restriction-14.0.1.2.1.dist-info/top_level.txt
odoo14_addon_stock_location_package_restriction-14.0.1.2.1.dist-info/RECORD
